{
  "metadata": {
    "date": "2019-08-14T17:37:31.4738681-05:00",
    "language": "eng",
    "total_words": 50,
    "total_candidates": 13,
    "total_names": 1
  },
  "names": [
    {
      "type": "PossibleBinomial",
      "verbatim": "Coanothera pallida",
      "name": "Coanothera pallida",
      "odds": 14660.70473118528,
      "odds_details": {
        "Name": {
          "uniDict": {
            "NotInDictionary": 0.01045703851117512
          },
          "abbr": {
            "false": 0.8679430877999654
          },
          "uniEnd3": {
            "era": 36.428449195707756
          },
          "spLen": {
            "7": 4.425451988126818
          },
          "spDict": {
            "WhiteSpecies": 5628.6125203841275
          },
          "spEnd3": {
            "ida": 202.72014857764088
          },
          "PriorOdds": {
            "true": 0.1
          },
          "uniLen": {
            "10": 3.1988876638791726
          }
        }
      },
      "start": 252,
      "end": 270,
      "annotation": "",
      "verification": {
        "BestResult": {
          "matchType": "NoMatch"
        },
        "retries": 1
      }
    }
  ]
}
